[
  {
    "name": "Eagle",
    "source": "Basic Rules (2014)",
    "cr": 0,
    "type_str": "Beast",
    "size": "S",
    "pp": 14,
    "image_url": "https://www.dndbeyond.com/avatars/thumbnails/30849/292/1000/1000/638064498871776868.png",
    "token": "rbanw",
    "named": false
  },
  {
    "name": "Eala",
    "source": "Tome of Beasts 1",
    "cr": 2,
    "type_str": "Monstrosity",
    "size": "S",
    "pp": 10,
    "image_url": "",
    "token": "",
    "named": false
  },
  {
    "name": "Earth Elemental",
    "source": "Basic Rules (2014)",
    "cr": 5,
    "type_str": "Elemental",
    "size": "L",
    "pp": 10,
    "image_url": "https://www.dndbeyond.com/avatars/thumbnails/30783/692/1000/1000/638062015664899420.png",
    "token": "bnu5g",
    "named": false
  },
  {
    "name": "Earth Elemental Myrmidon",
    "source": "Mordenkainen Presents: Monsters of the Multiverse",
    "cr": 7,
    "type_str": "Elemental",
    "size": "M",
    "pp": 10,
    "image_url": "",
    "token": "",
    "named": false
  },
  {
    "name": "Eater of Dust",
    "source": "Tome of Beasts 1",
    "cr": 9,
    "type_str": "Aberration",
    "size": "M",
    "pp": 10,
    "image_url": "",
    "token": "",
    "named": false
  },
  {
    "name": "Eater of Hope",
    "source": "Mythic Odysseys of Theros",
    "cr": 6,
    "type_str": "Fiend",
    "size": "L",
    "pp": 10,
    "image_url": "",
    "token": "",
    "named": false
  },
  {
    "name": "Eater of Knowledge",
    "source": "Planescape: Adventures in the Multiverse",
    "cr": 6,
    "type_str": "Aberration",
    "size": "L",
    "pp": 10,
    "image_url": "",
    "token": "",
    "named": false
  },
  {
    "name": "Eblis",
    "source": "Tomb of Annihilation",
    "cr": 1,
    "type_str": "Monstrosity",
    "size": "L",
    "pp": 10,
    "image_url": "",
    "token": "",
    "named": false
  },
  {
    "name": "Echo of Demogorgon",
    "source": "Bigby Presents: Glory of the Giants",
    "cr": 6,
    "type_str": "Fiend",
    "size": "L",
    "pp": 10,
    "image_url": "",
    "token": "",
    "named": false
  },
  {
    "name": "Edimmu",
    "source": "Tome of Beasts 1",
    "cr": 4,
    "type_str": "Undead",
    "size": "M",
    "pp": 10,
    "image_url": "",
    "token": "",
    "named": false
  },
  {
    "name": "Eel Hound",
    "source": "Tome of Beasts 1",
    "cr": 2,
    "type_str": "Fey",
    "size": "M",
    "pp": 10,
    "image_url": "",
    "token": "",
    "named": false
  },
  {
    "name": "Effulgent Cnidarian",
    "source": "Monsters of Drakkenheim",
    "cr": 9,
    "type_str": "Aberration",
    "size": "L",
    "pp": 10,
    "image_url": "",
    "token": "",
    "named": false
  },
  {
    "name": "Efreeti",
    "source": "Basic Rules (2014)",
    "cr": 11,
    "type_str": "Elemental",
    "size": "L",
    "pp": 12,
    "image_url": "https://www.dndbeyond.com/avatars/thumbnails/30784/76/1000/1000/638062028391329539.png",
    "token": "876bz",
    "named": false
  },
  {
    "name": "Egg Hunter Adult",
    "source": "Fizban's Treasury of Dragons",
    "cr": 5,
    "type_str": "Monstrosity",
    "size": "S",
    "pp": 10,
    "image_url": "",
    "token": "",
    "named": false
  },
  {
    "name": "Egg Hunter Hatchling",
    "source": "Fizban's Treasury of Dragons",
    "cr": 2,
    "type_str": "Monstrosity",
    "size": "T",
    "pp": 10,
    "image_url": "",
    "token": "",
    "named": false
  },
  {
    "name": "Eidolon",
    "source": "Mordenkainen's Tome of Foes",
    "cr": 12,
    "type_str": "Undead",
    "size": "M",
    "pp": 10,
    "image_url": "",
    "token": "",
    "named": false
  },
  {
    "name": "Eigeron’s Spirit",
    "source": "Storm King's Thunder",
    "cr": 4,
    "type_str": "Undead",
    "size": "H",
    "pp": 10,
    "image_url": "",
    "token": "",
    "named": false
  },
  {
    "name": "Einherjar",
    "source": "Tome of Beasts 1",
    "cr": 7,
    "type_str": "Humanoid",
    "size": "M",
    "pp": 10,
    "image_url": "",
    "token": "",
    "named": false
  },
  {
    "name": "Elder Black Pudding",
    "source": "Tales from the Yawning Portal",
    "cr": 4,
    "type_str": "Ooze",
    "size": "H",
    "pp": 10,
    "image_url": "",
    "token": "",
    "named": false
  },
  {
    "name": "Elder Brain",
    "source": "Mordenkainen Presents: Monsters of the Multiverse",
    "cr": 14,
    "type_str": "Aberration",
    "size": "L",
    "pp": 10,
    "image_url": "",
    "token": "",
    "named": false
  },
  {
    "name": "Elder Brain Dragon",
    "source": "Fizban's Treasury of Dragons",
    "cr": 22,
    "type_str": "Aberration",
    "size": "G",
    "pp": 10,
    "image_url": "",
    "token": "",
    "named": false
  },
  {
    "name": "Elder Lava Wurm",
    "source": "The Griffon's Saddlebag: Book Two",
    "cr": 7,
    "type_str": "Dragon",
    "size": "L",
    "pp": 10,
    "image_url": "",
    "token": "",
    "named": false
  },
  {
    "name": "Elder Oblex",
    "source": "Mordenkainen Presents: Monsters of the Multiverse",
    "cr": 10,
    "type_str": "Ooze",
    "size": "H",
    "pp": 10,
    "image_url": "",
    "token": "",
    "named": false
  },
  {
    "name": "Elder Shadow Drake",
    "source": "Tome of Beasts 1",
    "cr": 7,
    "type_str": "Dragon",
    "size": "L",
    "pp": 10,
    "image_url": "",
    "token": "",
    "named": false
  },
  {
    "name": "Elder Tempest",
    "source": "Mordenkainen Presents: Monsters of the Multiverse",
    "cr": 23,
    "type_str": "Elemental",
    "size": "G",
    "pp": 10,
    "image_url": "",
    "token": "",
    "named": false
  },
  {
    "name": "Eldrick Runeweaver",
    "source": "Monsters of Drakkenheim",
    "cr": 15,
    "type_str": "Humanoid",
    "size": "M",
    "pp": 10,
    "image_url": "",
    "token": "",
    "named": false
  },
  {
    "name": "Eldritch Cataclysm",
    "source": "Monsters of Drakkenheim",
    "cr": 13,
    "type_str": "Elemental",
    "size": "G",
    "pp": 10,
    "image_url": "",
    "token": "",
    "named": false
  },
  {
    "name": "Eldritch Crawler",
    "source": "Monsters of Drakkenheim",
    "cr": 3,
    "type_str": "Aberration",
    "size": "M",
    "pp": 10,
    "image_url": "",
    "token": "",
    "named": false
  },
  {
    "name": "Eldritch Dreg",
    "source": "Monsters of Drakkenheim",
    "cr": 3,
    "type_str": "Aberration",
    "size": "M",
    "pp": 10,
    "image_url": "",
    "token": "",
    "named": false
  },
  {
    "name": "Eldritch Herald",
    "source": "Lairs of Etharis",
    "cr": 5,
    "type_str": "Humanoid",
    "size": "M",
    "pp": 10,
    "image_url": "",
    "token": "",
    "named": false
  },
  {
    "name": "Eldritch Horror Hatchling",
    "source": "Keys from the Golden Vault",
    "cr": 2,
    "type_str": "Monstrosity",
    "size": "L",
    "pp": 10,
    "image_url": "",
    "token": "",
    "named": false
  },
  {
    "name": "Eldritch Priest",
    "source": "Lairs of Etharis",
    "cr": 2,
    "type_str": "Humanoid",
    "size": "M",
    "pp": 10,
    "image_url": "",
    "token": "",
    "named": false
  },
  {
    "name": "Eldritch Trickster",
    "source": "Monsters of Drakkenheim",
    "cr": 4,
    "type_str": "Humanoid",
    "size": "M",
    "pp": 10,
    "image_url": "",
    "token": "",
    "named": false
  },
  {
    "name": "Eldritch Troll",
    "source": "Monsters of Drakkenheim",
    "cr": 8,
    "type_str": "Giant",
    "size": "L",
    "pp": 10,
    "image_url": "",
    "token": "",
    "named": false
  },
  {
    "name": "Elemental Locus",
    "source": "Tome of Beasts 1",
    "cr": 17,
    "type_str": "Elemental",
    "size": "G",
    "pp": 10,
    "image_url": "",
    "token": "",
    "named": false
  },
  {
    "name": "Elephant",
    "source": "Basic Rules (2014)",
    "cr": 4,
    "type_str": "Beast",
    "size": "H",
    "pp": 10,
    "image_url": "",
    "token": "",
    "named": false
  },
  {
    "name": "Elf Vampire (Ancient)",
    "source": "Lairs of Etharis",
    "cr": 19,
    "type_str": "Undead",
    "size": "M",
    "pp": 10,
    "image_url": "",
    "token": "",
    "named": false
  },
  {
    "name": "Eliphas Adulare",
    "source": "Keys from the Golden Vault",
    "cr": 5,
    "type_str": "Humanoid",
    "size": "M",
    "pp": 10,
    "image_url": "",
    "token": "",
    "named": true
  },
  {
    "name": "Elise",
    "source": "Van Richten's Guide to Ravenloft",
    "cr": 5,
    "type_str": "Construct",
    "size": "M",
    "pp": 10,
    "image_url": "",
    "token": "",
    "named": false
  },
  {
    "name": "Elister Noggins",
    "source": "Storm King's Thunder",
    "cr": 2,
    "type_str": "Humanoid",
    "size": "S",
    "pp": 10,
    "image_url": "",
    "token": "",
    "named": true
  },
  {
    "name": "Elizar Dryflagon",
    "source": "Princes of the Apocalypse",
    "cr": 5,
    "type_str": "Humanoid",
    "size": "M",
    "pp": 10,
    "image_url": "",
    "token": "",
    "named": true
  },
  {
    "name": "Elk",
    "source": "Basic Rules (2014)",
    "cr": 0.25,
    "type_str": "Beast",
    "size": "L",
    "pp": 10,
    "image_url": "",
    "token": "",
    "named": false
  },
  {
    "name": "Elkhorn",
    "source": "The Wild Beyond the Witchlight",
    "cr": 2,
    "type_str": "Humanoid",
    "size": "M",
    "pp": 10,
    "image_url": "",
    "token": "",
    "named": false
  },
  {
    "name": "Elora Quickwit",
    "source": "Humblewood Tales",
    "cr": 2,
    "type_str": "Humanoid",
    "size": "M",
    "pp": 10,
    "image_url": "",
    "token": "",
    "named": true
  },
  {
    "name": "Elvish Veteran Archer",
    "source": "Tome of Beasts 1",
    "cr": 3,
    "type_str": "Humanoid",
    "size": "M",
    "pp": 10,
    "image_url": "",
    "token": "",
    "named": false
  },
  {
    "name": "Ember Roc",
    "source": "Tal'Dorei Campaign Setting Reborn",
    "cr": 14,
    "type_str": "Monstrosity",
    "size": "G",
    "pp": 10,
    "image_url": "",
    "token": "",
    "named": false
  },
  {
    "name": "Emberosa",
    "source": "Waterdeep: Dungeon of the Mad Mage",
    "cr": 9,
    "type_str": "Giant",
    "size": "H",
    "pp": 10,
    "image_url": "",
    "token": "",
    "named": true
  },
  {
    "name": "Embric",
    "source": "Waterdeep: Dragon Heist",
    "cr": 2,
    "type_str": "Humanoid",
    "size": "M",
    "pp": 10,
    "image_url": "",
    "token": "",
    "named": true
  },
  {
    "name": "Emerald Dragon Wyrmling",
    "source": "Fizban's Treasury of Dragons",
    "cr": 2,
    "type_str": "Dragon",
    "size": "M",
    "pp": 10,
    "image_url": "",
    "token": "",
    "named": false
  },
  {
    "name": "Emerald Enclave Scout",
    "source": "Out of the Abyss",
    "cr": 0.5,
    "type_str": "Humanoid",
    "size": "M",
    "pp": 10,
    "image_url": "",
    "token": "",
    "named": false
  },
  {
    "name": "Emerald Eye",
    "source": "Tome of Beasts 1",
    "cr": 1,
    "type_str": "Construct",
    "size": "T",
    "pp": 10,
    "image_url": "",
    "token": "",
    "named": false
  },
  {
    "name": "Emerald Greatwyrm",
    "source": "Fizban's Treasury of Dragons",
    "cr": 26,
    "type_str": "Dragon",
    "size": "G",
    "pp": 10,
    "image_url": "",
    "token": "",
    "named": false
  },
  {
    "name": "Emerald Order Cult Leader",
    "source": "Tome of Beasts 1",
    "cr": 8,
    "type_str": "Humanoid",
    "size": "M",
    "pp": 10,
    "image_url": "",
    "token": "",
    "named": false
  },
  {
    "name": "Empty Cloak",
    "source": "Tome of Beasts 1",
    "cr": 0.5,
    "type_str": "Construct",
    "size": "M",
    "pp": 10,
    "image_url": "",
    "token": "",
    "named": false
  },
  {
    "name": "Empyrean",
    "source": "Monster Manual (2014)",
    "cr": 23,
    "type_str": "Celestial",
    "size": "H",
    "pp": 10,
    "image_url": "",
    "token": "",
    "named": false
  },
  {
    "name": "Empyrean Brazen Bull",
    "source": "Lairs of Etharis",
    "cr": 10,
    "type_str": "Celestial",
    "size": "H",
    "pp": 10,
    "image_url": "",
    "token": "",
    "named": false
  },
  {
    "name": "Encephalon Cluster",
    "source": "Phandelver and Below: The Shattered Obelisk",
    "cr": 10,
    "type_str": "Aberration",
    "size": "L",
    "pp": 10,
    "image_url": "",
    "token": "",
    "named": false
  },
  {
    "name": "Encephalon Gemmule",
    "source": "Phandelver and Below: The Shattered Obelisk",
    "cr": 3,
    "type_str": "Aberration",
    "size": "T",
    "pp": 10,
    "image_url": "",
    "token": "",
    "named": false
  },
  {
    "name": "Enchanter",
    "source": "Volo's Guide to Monsters",
    "cr": 5,
    "type_str": "Humanoid",
    "size": "M",
    "pp": 10,
    "image_url": "",
    "token": "",
    "named": false
  },
  {
    "name": "Enchanter Wizard",
    "source": "Mordenkainen Presents: Monsters of the Multiverse",
    "cr": 5,
    "type_str": "Humanoid",
    "size": "M",
    "pp": 10,
    "image_url": "",
    "token": "",
    "named": false
  },
  {
    "name": "Enchanting Infiltrator",
    "source": "The Book of Many Things",
    "cr": 11,
    "type_str": "Fey",
    "size": "M",
    "pp": 10,
    "image_url": "",
    "token": "",
    "named": false
  },
  {
    "name": "Endelyn Moongrave",
    "source": "The Wild Beyond the Witchlight",
    "cr": 6,
    "type_str": "Fey",
    "size": "M",
    "pp": 10,
    "image_url": "",
    "token": "",
    "named": false
  },
  {
    "name": "Enhanced Medusa",
    "source": "Infernal Machine Rebuild",
    "cr": 6,
    "type_str": "Monstrosity",
    "size": "M",
    "pp": 10,
    "image_url": "",
    "token": "",
    "named": false
  },
  {
    "name": "Enormous Tentacle",
    "source": "Acquisitions Incorporated",
    "cr": 2,
    "type_str": "Beast",
    "size": "H",
    "pp": 10,
    "image_url": "",
    "token": "",
    "named": false
  },
  {
    "name": "Entropic Flame",
    "source": "Monsters of Drakkenheim",
    "cr": 5,
    "type_str": "Elemental",
    "size": "L",
    "pp": 10,
    "image_url": "",
    "token": "",
    "named": false
  },
  {
    "name": "Entropic Watcher",
    "source": "Monsters of Drakkenheim",
    "cr": 15,
    "type_str": "Aberration",
    "size": "L",
    "pp": 10,
    "image_url": "",
    "token": "",
    "named": false
  },
  {
    "name": "Envy",
    "source": "The Wild Beyond the Witchlight",
    "cr": 5,
    "type_str": "Monstrosity",
    "size": "L",
    "pp": 10,
    "image_url": "",
    "token": "",
    "named": true
  },
  {
    "name": "Eoghan Ghostweaver",
    "source": "Dungeons of Drakkenheim",
    "cr": 12,
    "type_str": "Humanoid",
    "size": "M",
    "pp": 10,
    "image_url": "",
    "token": "",
    "named": false
  },
  {
    "name": "Eonic Drifter",
    "source": "Tome of Beasts 1",
    "cr": 1,
    "type_str": "Humanoid",
    "size": "M",
    "pp": 10,
    "image_url": "",
    "token": "",
    "named": false
  },
  {
    "name": "Equinal Guardinal",
    "source": "Planescape: Adventures in the Multiverse",
    "cr": 6,
    "type_str": "Celestial",
    "size": "L",
    "pp": 10,
    "image_url": "",
    "token": "",
    "named": false
  },
  {
    "name": "Erestee Loff",
    "source": "Tales from the Shadows",
    "cr": 2,
    "type_str": "Humanoid",
    "size": "S",
    "pp": 10,
    "image_url": "",
    "token": "",
    "named": true
  },
  {
    "name": "Erina",
    "source": "Tome of Beasts 1",
    "cr": 0.25,
    "type_str": "Humanoid",
    "size": "S",
    "pp": 10,
    "image_url": "",
    "token": "",
    "named": false
  },
  {
    "name": "Erina Defender",
    "source": "Tome of Beasts 1",
    "cr": 1,
    "type_str": "Humanoid",
    "size": "S",
    "pp": 10,
    "image_url": "",
    "token": "",
    "named": false
  },
  {
    "name": "Erinyes",
    "source": "Basic Rules (2014)",
    "cr": 12,
    "type_str": "Fiend",
    "size": "M",
    "pp": 12,
    "image_url": "https://www.dndbeyond.com/avatars/thumbnails/30782/8/1000/1000/638061948096035985.png",
    "token": "wjuud",
    "named": false
  },
  {
    "name": "Erinyes (Rope Variant)",
    "source": "Monster Manual (2014)",
    "cr": 12,
    "type_str": "Fiend",
    "size": "M",
    "pp": 10,
    "image_url": "",
    "token": "",
    "named": false
  },
  {
    "name": "Erinyes (Summoner Variant)",
    "source": "Monster Manual (2014)",
    "cr": 12,
    "type_str": "Fiend",
    "size": "M",
    "pp": 10,
    "image_url": "",
    "token": "",
    "named": false
  },
  {
    "name": "Erky Timbers",
    "source": "Tales from the Yawning Portal",
    "cr": 0.25,
    "type_str": "Humanoid",
    "size": "S",
    "pp": 10,
    "image_url": "",
    "token": "",
    "named": true
  },
  {
    "name": "Esthetic",
    "source": "Spelljammer: Adventures in Space",
    "cr": 12,
    "type_str": "Aberration",
    "size": "G",
    "pp": 10,
    "image_url": "",
    "token": "",
    "named": false
  },
  {
    "name": "Estia",
    "source": "Tales from the Yawning Portal",
    "cr": 9,
    "type_str": "Giant",
    "size": "H",
    "pp": 10,
    "image_url": "",
    "token": "",
    "named": true
  },
  {
    "name": "Eternal Flame Guardian",
    "source": "Princes of the Apocalypse",
    "cr": 2,
    "type_str": "Humanoid",
    "size": "M",
    "pp": 10,
    "image_url": "",
    "token": "",
    "named": false
  },
  {
    "name": "Eternal Flame Priest",
    "source": "Princes of the Apocalypse",
    "cr": 3,
    "type_str": "Humanoid",
    "size": "M",
    "pp": 10,
    "image_url": "",
    "token": "",
    "named": false
  },
  {
    "name": "Ether Fish",
    "source": "The Griffon's Saddlebag: Book Two",
    "cr": 0.125,
    "type_str": "Monstrosity",
    "size": "T",
    "pp": 10,
    "image_url": "",
    "token": "",
    "named": false
  },
  {
    "name": "Etherean Trickster",
    "source": "The Griffon's Saddlebag: Book Two",
    "cr": 0.5,
    "type_str": "Humanoid",
    "size": "M",
    "pp": 10,
    "image_url": "",
    "token": "",
    "named": false
  },
  {
    "name": "Ettercap",
    "source": "Basic Rules (2014)",
    "cr": 2,
    "type_str": "Monstrosity",
    "size": "M",
    "pp": 13,
    "image_url": "https://www.dndbeyond.com/avatars/thumbnails/30783/716/1000/1000/638062016297389481.png",
    "token": "cnvxg",
    "named": false
  },
  {
    "name": "Ettercap (variant)",
    "source": "Monster Manual (2014)",
    "cr": 2,
    "type_str": "Monstrosity",
    "size": "M",
    "pp": 10,
    "image_url": "",
    "token": "",
    "named": false
  },
  {
    "name": "Ettin",
    "source": "Basic Rules (2014)",
    "cr": 4,
    "type_str": "Giant",
    "size": "L",
    "pp": 14,
    "image_url": "https://www.dndbeyond.com/avatars/thumbnails/30783/726/1000/1000/638062016402079484.png",
    "token": "6ekzp",
    "named": false
  },
  {
    "name": "Ettin Ceremorph",
    "source": "Bigby Presents: Glory of the Giants",
    "cr": 8,
    "type_str": "Aberration",
    "size": "L",
    "pp": 10,
    "image_url": "",
    "token": "",
    "named": false
  },
  {
    "name": "Euryale",
    "source": "The Book of Many Things",
    "cr": 18,
    "type_str": "Monstrosity",
    "size": "M",
    "pp": 10,
    "image_url": "",
    "token": "",
    "named": true
  },
  {
    "name": "Everbug",
    "source": "Humblewood Tales",
    "cr": 0,
    "type_str": "Beast",
    "size": "T",
    "pp": 10,
    "image_url": "",
    "token": "",
    "named": false
  },
  {
    "name": "Evil Mage",
    "source": "Lost Mine of Phandelver",
    "cr": 1,
    "type_str": "Humanoid",
    "size": "M",
    "pp": 10,
    "image_url": "",
    "token": "",
    "named": false
  },
  {
    "name": "Evoker",
    "source": "Volo's Guide to Monsters",
    "cr": 9,
    "type_str": "Humanoid",
    "size": "M",
    "pp": 10,
    "image_url": "",
    "token": "",
    "named": false
  },
  {
    "name": "Evoker Wizard",
    "source": "Mordenkainen Presents: Monsters of the Multiverse",
    "cr": 9,
    "type_str": "Humanoid",
    "size": "M",
    "pp": 10,
    "image_url": "",
    "token": "",
    "named": false
  },
  {
    "name": "Executioner",
    "source": "Monsters of Drakkenheim",
    "cr": 25,
    "type_str": "Construct",
    "size": "H",
    "pp": 10,
    "image_url": "",
    "token": "",
    "named": false
  },
  {
    "name": "Exethanter",
    "source": "Curse of Strahd",
    "cr": 10,
    "type_str": "Undead",
    "size": "M",
    "pp": 10,
    "image_url": "",
    "token": "",
    "named": false
  },
  {
    "name": "Exorcist",
    "source": "Monsters of Drakkenheim",
    "cr": 8,
    "type_str": "Humanoid",
    "size": "M",
    "pp": 10,
    "image_url": "",
    "token": "",
    "named": false
  },
  {
    "name": "Expeditious Messenger",
    "source": "Eberron: Rising from the Last War",
    "cr": 0.125,
    "type_str": "Construct",
    "size": "T",
    "pp": 10,
    "image_url": "",
    "token": "",
    "named": false
  },
  {
    "name": "Expert",
    "source": "Dragon of Icespire Peak",
    "cr": 1,
    "type_str": "Humanoid",
    "size": "M",
    "pp": 10,
    "image_url": "",
    "token": "",
    "named": false
  },
  {
    "name": "Eye Crawler",
    "source": "Lairs of Etharis",
    "cr": 0,
    "type_str": "Aberration",
    "size": "T",
    "pp": 10,
    "image_url": "",
    "token": "",
    "named": false
  },
  {
    "name": "Eye Crow",
    "source": "Lairs of Etharis",
    "cr": 0,
    "type_str": "Beast",
    "size": "T",
    "pp": 10,
    "image_url": "",
    "token": "",
    "named": false
  },
  {
    "name": "Eye Golem",
    "source": "Tome of Beasts 1",
    "cr": 11,
    "type_str": "Construct",
    "size": "L",
    "pp": 10,
    "image_url": "",
    "token": "",
    "named": false
  },
  {
    "name": "Eye Monger",
    "source": "Spelljammer: Adventures in Space",
    "cr": 10,
    "type_str": "Aberration",
    "size": "L",
    "pp": 10,
    "image_url": "",
    "token": "",
    "named": false
  },
  {
    "name": "Eye of Fear and Flame",
    "source": "Infernal Machine Rebuild",
    "cr": 9,
    "type_str": "Undead",
    "size": "M",
    "pp": 10,
    "image_url": "",
    "token": "",
    "named": false
  },
  {
    "name": "Eyedrake",
    "source": "Fizban's Treasury of Dragons",
    "cr": 8,
    "type_str": "Aberration",
    "size": "L",
    "pp": 10,
    "image_url": "",
    "token": "",
    "named": false
  },
  {
    "name": "Eyestalk of Gzemnid",
    "source": "Planescape: Adventures in the Multiverse",
    "cr": 15,
    "type_str": "Monstrosity",
    "size": "G",
    "pp": 10,
    "image_url": "",
    "token": "",
    "named": false
  },
  {
    "name": "Ezmerelda d'Avenir",
    "source": "Curse of Strahd",
    "cr": 8,
    "type_str": "Humanoid",
    "size": "M",
    "pp": 10,
    "image_url": "",
    "token": "",
    "named": true
  }
]
