{
  "workshop": {
    "id": "6a1a4e9a65f5e47e3a890691",
    "environment": "c9028316-9197-4da5-9fd3-bbb040563c05"
  },
  "aliases": [
    {
      "name": "westmarch",
      "file": "src/aliases/westmarch/westmarch.alias",
      "docs_file": "src/aliases/westmarch/westmarch.md",
      "sub_aliases": [
        {
          "name": "setup",
          "file": "src/aliases/westmarch/setup.alias",
          "docs_file": "src/aliases/westmarch/setup.md"
        },
        {
          "name": "show",
          "file": "src/aliases/westmarch/show.alias",
          "docs_file": "src/aliases/westmarch/show.md"
        }
      ]
    },
    {
      "name": "enc",
      "file": "src/aliases/exploration/enc.alias",
      "docs_file": "src/aliases/exploration/enc.md"
    },
    {
      "name": "forage",
      "file": "src/aliases/exploration/forage.alias",
      "docs_file": "src/aliases/exploration/forage.md"
    },
    {
      "name": "fish",
      "file": "src/aliases/exploration/fish.alias",
      "docs_file": "src/aliases/exploration/fish.md"
    },
    {
      "name": "mine",
      "file": "src/aliases/exploration/mine.alias",
      "docs_file": "src/aliases/exploration/mine.md"
    },
    {
      "name": "lumber",
      "file": "src/aliases/exploration/lumber.alias",
      "docs_file": "src/aliases/exploration/lumber.md"
    },
    {
      "name": "hunt",
      "file": "src/aliases/exploration/hunt.alias",
      "docs_file": "src/aliases/exploration/hunt.md"
    },
    {
      "name": "loot",
      "file": "src/aliases/exploration/loot.alias",
      "docs_file": "src/aliases/exploration/loot.md"
    },
    {
      "name": "travel",
      "file": "src/aliases/travel/travel.alias",
      "docs_file": "src/aliases/travel/travel.md"
    },
    {
      "name": "location",
      "file": "src/aliases/travel/location.alias",
      "docs_file": "src/aliases/travel/location.md"
    },
    {
      "name": "time",
      "file": "src/aliases/travel/time.alias",
      "docs_file": "src/aliases/travel/time.md"
    },
    {
      "name": "weather",
      "file": "src/aliases/travel/weather.alias",
      "docs_file": "src/aliases/travel/weather.md"
    },
    {
      "name": "downtime",
      "file": "src/aliases/downtime/downtime.alias",
      "docs_file": "src/aliases/downtime/downtime.md"
    },
    {
      "name": "craft",
      "file": "src/aliases/crafting/craft.alias",
      "docs_file": "src/aliases/crafting/craft.md"
    },
    {
      "name": "brew",
      "file": "src/aliases/crafting/brew.alias",
      "docs_file": "src/aliases/crafting/brew.md"
    },
    {
      "name": "enchant",
      "file": "src/aliases/crafting/enchant.alias",
      "docs_file": "src/aliases/crafting/enchant.md"
    },
    {
      "name": "scribe",
      "file": "src/aliases/crafting/scribe.alias",
      "docs_file": "src/aliases/crafting/scribe.md"
    },
    {
      "name": "job",
      "file": "src/aliases/economy/job.alias",
      "docs_file": "src/aliases/economy/job.md"
    },
    {
      "name": "buy",
      "file": "src/aliases/economy/buy.alias",
      "docs_file": "src/aliases/economy/buy.md"
    },
    {
      "name": "sell",
      "file": "src/aliases/economy/sell.alias",
      "docs_file": "src/aliases/economy/sell.md"
    },
    {
      "name": "wallet",
      "file": "src/aliases/economy/wallet.alias",
      "docs_file": "src/aliases/economy/wallet.md"
    },
    {
      "name": "library",
      "file": "src/aliases/content/library.alias",
      "docs_file": "src/aliases/content/library.md"
    },
    {
      "name": "read",
      "file": "src/aliases/content/read.alias",
      "docs_file": "src/aliases/content/read.md"
    },
    {
      "name": "quest",
      "file": "src/aliases/misc/quest.alias",
      "docs_file": "src/aliases/misc/quest.md"
    },
    {
      "name": "recipe",
      "file": "src/aliases/misc/recipe.alias",
      "docs_file": "src/aliases/misc/recipe.md"
    }
  ],
  "snippets": [],
  "gvars": [
    {
      "name": "env",
      "file": "src/gvars/env.prod.gvar",
      "id": "c9028316-9197-4da5-9fd3-bbb040563c05"
    },
    {
      "name": "auth",
      "file": "src/gvars/utils/auth/auth.gvar",
      "id": "a3126246-4c37-42a6-b9e3-df2d1c57e821"
    },
    {
      "name": "bags",
      "file": "src/gvars/utils/core/bags.gvar",
      "id": "dfc7333d-ebba-4cb9-9408-954f54084b24"
    },
    {
      "name": "biome_astral",
      "file": "src/gvars/configs/biomes/biome_astral.gvar.json",
      "id": "856b1c4a-3605-41a3-9a5a-78dca4834550"
    },
    {
      "name": "biome_beach",
      "file": "src/gvars/configs/biomes/biome_beach.gvar.json",
      "id": "d1560630-749a-413a-96de-1503473ea1cf"
    },
    {
      "name": "biome_cave",
      "file": "src/gvars/configs/biomes/biome_cave.gvar.json",
      "id": "23aa3400-8454-43cb-84f7-3dca02e7792d"
    },
    {
      "name": "biome_deep_seas",
      "file": "src/gvars/configs/biomes/biome_deep_seas.gvar.json",
      "id": "68952141-d94d-408e-b674-c8048dad5c56"
    },
    {
      "name": "biome_desert",
      "file": "src/gvars/configs/biomes/biome_desert.gvar.json",
      "id": "20bf41a5-f3f4-497a-9568-6b267e51d465"
    },
    {
      "name": "biome_forest",
      "file": "src/gvars/configs/biomes/biome_forest.gvar.json",
      "id": "dead1004-4dcf-4424-8562-800301b8563c"
    },
    {
      "name": "biome_jungle",
      "file": "src/gvars/configs/biomes/biome_jungle.gvar.json",
      "id": "818a8ed9-b651-439c-a481-fa83e933b647"
    },
    {
      "name": "biome_mountain",
      "file": "src/gvars/configs/biomes/biome_mountain.gvar.json",
      "id": "e1187779-dfc3-4f5e-bbe5-3b186ed402f3"
    },
    {
      "name": "biome_plains",
      "file": "src/gvars/configs/biomes/biome_plains.gvar.json",
      "id": "fffff9be-cb04-4cb8-a0cf-93b6c93244e9"
    },
    {
      "name": "biome_river",
      "file": "src/gvars/configs/biomes/biome_river.gvar.json",
      "id": "06d1bbd7-1acb-47d9-90f2-0e3adee7e3af"
    },
    {
      "name": "biome_road",
      "file": "src/gvars/configs/biomes/biome_road.gvar.json",
      "id": "1f9b5428-1490-4ace-bd1f-7bc264a792f0"
    },
    {
      "name": "biome_ruins",
      "file": "src/gvars/configs/biomes/biome_ruins.gvar.json",
      "id": "5cbc8bf2-e7ab-440b-ac11-bb1879e844aa"
    },
    {
      "name": "biome_sea",
      "file": "src/gvars/configs/biomes/biome_sea.gvar.json",
      "id": "e74e7d44-daa6-44df-8f06-2d85e9a49b70"
    },
    {
      "name": "biome_sky",
      "file": "src/gvars/configs/biomes/biome_sky.gvar.json",
      "id": "d8d67f87-4b64-4cd7-921a-aecb2879c649"
    },
    {
      "name": "biome_swamp",
      "file": "src/gvars/configs/biomes/biome_swamp.gvar.json",
      "id": "200659a1-3149-4b03-b5a5-eaed3cfbd39a"
    },
    {
      "name": "biome_tundra",
      "file": "src/gvars/configs/biomes/biome_tundra.gvar.json",
      "id": "ac804553-dc07-475f-b2ef-2780eb605616"
    },
    {
      "name": "biome_underdark",
      "file": "src/gvars/configs/biomes/biome_underdark.gvar.json",
      "id": "e27d2c2a-1436-4966-86ea-48ea20899cdc"
    },
    {
      "name": "biome_urban",
      "file": "src/gvars/configs/biomes/biome_urban.gvar.json",
      "id": "e1e3d2f3-cfa8-481e-8169-c0c7cc018f0a"
    },
    {
      "name": "biome_volcanic",
      "file": "src/gvars/configs/biomes/biome_volcanic.gvar.json",
      "id": "f935b7c3-87ee-4eb8-a84d-5b5a25532834"
    },
    {
      "name": "biome_wm_cave",
      "file": "src/gvars/configs/biomes/biome_wm_cave.gvar.json",
      "id": "f8a09d7e-6c04-4f75-ad6f-c506817767a4"
    },
    {
      "name": "biome_wm_forest",
      "file": "src/gvars/configs/biomes/biome_wm_forest.gvar.json",
      "id": "c8a02a38-20c5-414a-be1d-1167af38753d"
    },
    {
      "name": "biome_wm_mountain",
      "file": "src/gvars/configs/biomes/biome_wm_mountain.gvar.json",
      "id": "5c74dc75-e92d-4dc3-9b19-32ac99795033"
    },
    {
      "name": "biome_wm_plains",
      "file": "src/gvars/configs/biomes/biome_wm_plains.gvar.json",
      "id": "1b0a9dc1-3c3d-453b-8c47-950caf08da36"
    },
    {
      "name": "biome_wm_river",
      "file": "src/gvars/configs/biomes/biome_wm_river.gvar.json",
      "id": "b35d2f3c-527b-43ae-aaa4-593c82eccded"
    },
    {
      "name": "biome_wm_road",
      "file": "src/gvars/configs/biomes/biome_wm_road.gvar.json",
      "id": "5df5f0ca-23c8-4368-a624-efb1da7061b0"
    },
    {
      "name": "biome_wm_sea",
      "file": "src/gvars/configs/biomes/biome_wm_sea.gvar.json",
      "id": "1c8ec498-a9a6-4a14-a687-15a8cf7e7c63"
    },
    {
      "name": "biome_wm_urban",
      "file": "src/gvars/configs/biomes/biome_wm_urban.gvar.json",
      "id": "e44ca71f-7bcd-4e4b-9b4a-e7d459a90a39"
    },
    {
      "name": "biomes",
      "file": "src/gvars/utils/world/biomes.gvar",
      "id": "e5871a1f-2dfa-4a5e-b556-75dbbf8d27bd"
    },
    {
      "name": "clock",
      "file": "src/gvars/utils/world/clock.gvar",
      "id": "5533ed6a-4483-45f3-b7ef-2a336fa7ddfe"
    },
    {
      "name": "commands",
      "file": "src/gvars/utils/core/commands.gvar",
      "id": "58dd877f-b654-4f80-a9be-1e3dd0450d56"
    },
    {
      "name": "config",
      "file": "src/gvars/utils/config/config.gvar",
      "id": "1d810d47-af5b-47d5-9595-0ff9900a00bf"
    },
    {
      "name": "crafting",
      "file": "src/gvars/utils/crafting/crafting.gvar",
      "id": "5bd54705-0f1a-46b9-9e8b-eef559cddb8e"
    },
    {
      "name": "dicts",
      "file": "src/gvars/utils/core/dicts.gvar",
      "id": "8d7b2b26-8026-4855-bc69-e55617dd95a9"
    },
    {
      "name": "display",
      "file": "src/gvars/utils/display/display.gvar",
      "id": "8dc8aae7-deb0-4f21-8f8a-2a101c33cc32"
    },
    {
      "name": "embeds",
      "file": "src/gvars/utils/core/embeds.gvar",
      "id": "d483bc13-362f-45c5-8596-efcab434123b"
    },
    {
      "name": "encounter_lists",
      "file": "src/gvars/utils/encounters/encounter_lists.gvar",
      "id": "7497adbc-f942-44ad-aae5-7fc72eb162dc"
    },
    {
      "name": "encounter_templates",
      "file": "src/gvars/utils/encounters/encounter_templates.gvar",
      "id": "5e41f89b-91f8-4554-8bed-440ff3781e4b"
    },
    {
      "name": "encounters",
      "file": "src/gvars/utils/encounters/encounters.gvar",
      "id": "2aabdcdb-3510-431b-8f35-afd06ff04224"
    },
    {
      "name": "exploration",
      "file": "src/gvars/utils/exploration/exploration.gvar",
      "id": "6b51c53f-3db9-49cd-8f24-e35866226fa2"
    },
    {
      "name": "forgotten_realms_2014_locations",
      "file": "src/gvars/configs/forgotten_realms_2014_locations.gvar.json",
      "id": "6c50e5a7-e36b-49fe-96e7-7e82e157bd31"
    },
    {
      "name": "forgotten_realms_2014_paths",
      "file": "src/gvars/configs/forgotten_realms_2014_paths.gvar.json",
      "id": "40403500-be2c-4b1a-8170-6176adf87aa5"
    },
    {
      "name": "forgotten_realms_a",
      "file": "src/gvars/configs/books/forgotten_realms_a.gvar.json",
      "id": "db6387b7-6856-4346-8601-8a326d856885"
    },
    {
      "name": "forgotten_realms_b",
      "file": "src/gvars/configs/books/forgotten_realms_b.gvar.json",
      "id": "02119878-36c4-4f9d-8aa7-468a440521a5"
    },
    {
      "name": "forgotten_realms_c",
      "file": "src/gvars/configs/books/forgotten_realms_c.gvar.json",
      "id": "e0ef1522-71ab-41f0-929b-71c397af8615"
    },
    {
      "name": "forgotten_realms_d",
      "file": "src/gvars/configs/books/forgotten_realms_d.gvar.json",
      "id": "725818d3-b318-4e3f-ae7d-cf31f1209cf7"
    },
    {
      "name": "forgotten_realms_e",
      "file": "src/gvars/configs/books/forgotten_realms_e.gvar.json",
      "id": "c4750f55-7874-4b82-b006-36b93859aa4c"
    },
    {
      "name": "forgotten_realms_f",
      "file": "src/gvars/configs/books/forgotten_realms_f.gvar.json",
      "id": "5b25fbcb-9308-45a4-8ba0-8c1b8c4ca4d3"
    },
    {
      "name": "forgotten_realms_g",
      "file": "src/gvars/configs/books/forgotten_realms_g.gvar.json",
      "id": "3bcf6923-b626-491d-a655-0a9c1634ba2c"
    },
    {
      "name": "forgotten_realms_h",
      "file": "src/gvars/configs/books/forgotten_realms_h.gvar.json",
      "id": "aedf732b-75e5-465a-aef9-6bfbc75cf260"
    },
    {
      "name": "forgotten_realms_i",
      "file": "src/gvars/configs/books/forgotten_realms_i.gvar.json",
      "id": "396f9804-c1c4-46d2-a99a-c77f82ad6418"
    },
    {
      "name": "forgotten_realms_j",
      "file": "src/gvars/configs/books/forgotten_realms_j.gvar.json",
      "id": "68f0c308-318a-446c-a0ad-c9d92ad0c779"
    },
    {
      "name": "forgotten_realms_k",
      "file": "src/gvars/configs/books/forgotten_realms_k.gvar.json",
      "id": "dd39c394-f150-48e2-8500-22f0417f331a"
    },
    {
      "name": "forgotten_realms_l",
      "file": "src/gvars/configs/books/forgotten_realms_l.gvar.json",
      "id": "5d9b408c-1b2d-4acd-947d-212dec6d41f9"
    },
    {
      "name": "forgotten_realms_m",
      "file": "src/gvars/configs/books/forgotten_realms_m.gvar.json",
      "id": "82f08053-8f69-4a07-ad7d-4cbec703cac9"
    },
    {
      "name": "forgotten_realms_n",
      "file": "src/gvars/configs/books/forgotten_realms_n.gvar.json",
      "id": "083b1b68-fa3c-491b-b726-9ce13d4c9568"
    },
    {
      "name": "forgotten_realms_o",
      "file": "src/gvars/configs/books/forgotten_realms_o.gvar.json",
      "id": "08b9df10-df71-44dc-aede-89c402e11abc"
    },
    {
      "name": "forgotten_realms_pq",
      "file": "src/gvars/configs/books/forgotten_realms_pq.gvar.json",
      "id": "55de7183-afd4-443d-8acb-4b1804f1ca45"
    },
    {
      "name": "forgotten_realms_r",
      "file": "src/gvars/configs/books/forgotten_realms_r.gvar.json",
      "id": "bc9c0712-c675-4c8a-9826-1e40959f61a5"
    },
    {
      "name": "forgotten_realms_s",
      "file": "src/gvars/configs/books/forgotten_realms_s.gvar.json",
      "id": "b4e96cb2-7ff8-49a0-9cec-8aaa51a7fba9"
    },
    {
      "name": "forgotten_realms_t",
      "file": "src/gvars/configs/books/forgotten_realms_t.gvar.json",
      "id": "ea9c7fab-8538-42c2-a0df-e537a20531be"
    },
    {
      "name": "forgotten_realms_v",
      "file": "src/gvars/configs/books/forgotten_realms_v.gvar.json",
      "id": "c5eef426-8036-41cf-8c7b-cf6e0d57eaf8"
    },
    {
      "name": "forgotten_realms_w",
      "file": "src/gvars/configs/books/forgotten_realms_w.gvar.json",
      "id": "ea8973e5-0590-4252-9a1d-b6121f8ebd0f"
    },
    {
      "name": "items",
      "file": "src/gvars/utils/catalogues/items/items.gvar",
      "id": "573a61f9-8b12-40e2-b296-cb5445c61edd"
    },
    {
      "name": "items_list",
      "file": "src/gvars/utils/catalogues/items/items_list.gvar.json",
      "id": "d1021306-0d9e-4874-8105-9003b81bdfef"
    },
    {
      "name": "journeys",
      "file": "src/gvars/utils/world/journeys.gvar",
      "id": "48d231dd-a0a9-496a-8834-38b062e063e4"
    },
    {
      "name": "languages",
      "file": "src/gvars/utils/core/languages.gvar",
      "id": "37e8d5c2-ac58-4811-a395-e1a475e66130"
    },
    {
      "name": "library",
      "file": "src/gvars/utils/content/library.gvar",
      "id": "43a10f5e-dd24-445d-b82d-f10ed989eff5"
    },
    {
      "name": "lists",
      "file": "src/gvars/utils/core/lists.gvar",
      "id": "ec3ed4c1-527f-40a8-9352-36cfeb7d59d6"
    },
    {
      "name": "location_encounters",
      "file": "src/gvars/utils/world/location_encounters.gvar",
      "id": "1b255e81-db11-4c9e-9e4d-01660f7cbdda"
    },
    {
      "name": "locations",
      "file": "src/gvars/utils/world/locations.gvar",
      "id": "f4cc9003-4fb4-41cb-8e06-98199b60d96b"
    },
    {
      "name": "loot",
      "file": "src/gvars/utils/exploration/loot.gvar",
      "id": "bbb9da79-aa74-40ec-9868-2075900bbfca"
    },
    {
      "name": "magic_items_list",
      "file": "src/gvars/utils/catalogues/items/magic_items_list.gvar.json",
      "id": "7d85da39-507e-466f-bd53-e57ff42558fb"
    },
    {
      "name": "monsters",
      "file": "src/gvars/utils/catalogues/monsters/monsters.gvar",
      "id": "64f20a33-f431-47c5-8a97-ca8abb0d3c9d"
    },
    {
      "name": "monsters_a",
      "file": "src/gvars/utils/catalogues/monsters/monsters_a.gvar.json",
      "id": "3251f862-418c-4ec4-b216-951439677f34"
    },
    {
      "name": "monsters_b",
      "file": "src/gvars/utils/catalogues/monsters/monsters_b.gvar.json",
      "id": "d513b5f7-3af2-4b07-b9cc-7724f1515e3b"
    },
    {
      "name": "monsters_c",
      "file": "src/gvars/utils/catalogues/monsters/monsters_c.gvar.json",
      "id": "a8027d7d-19b8-4e20-b433-1e92cce119fc"
    },
    {
      "name": "monsters_d",
      "file": "src/gvars/utils/catalogues/monsters/monsters_d.gvar.json",
      "id": "d3d2428b-5527-443a-b07c-c265292ad113"
    },
    {
      "name": "monsters_e",
      "file": "src/gvars/utils/catalogues/monsters/monsters_e.gvar.json",
      "id": "19177b4c-6d86-4b6b-9382-4861de76548a"
    },
    {
      "name": "monsters_f",
      "file": "src/gvars/utils/catalogues/monsters/monsters_f.gvar.json",
      "id": "a2165486-155c-4577-afb3-abbb216cbe44"
    },
    {
      "name": "monsters_g",
      "file": "src/gvars/utils/catalogues/monsters/monsters_g.gvar.json",
      "id": "84d6ba9a-0003-4ff6-aa09-d814ad4b9221"
    },
    {
      "name": "monsters_h",
      "file": "src/gvars/utils/catalogues/monsters/monsters_h.gvar.json",
      "id": "bc99078e-5c7c-4967-9324-c6c8dc39663b"
    },
    {
      "name": "monsters_i",
      "file": "src/gvars/utils/catalogues/monsters/monsters_i.gvar.json",
      "id": "b63dbe3b-44df-4885-8a57-ef5d61d98e89"
    },
    {
      "name": "monsters_j",
      "file": "src/gvars/utils/catalogues/monsters/monsters_j.gvar.json",
      "id": "18be1a3a-4345-4787-9e59-b9cf5570f1d6"
    },
    {
      "name": "monsters_k",
      "file": "src/gvars/utils/catalogues/monsters/monsters_k.gvar.json",
      "id": "b78b899b-20e5-47f8-8fa9-df8d39a4689a"
    },
    {
      "name": "monsters_l",
      "file": "src/gvars/utils/catalogues/monsters/monsters_l.gvar.json",
      "id": "3ea53d40-bdcf-48da-9c94-460fb9865ef7"
    },
    {
      "name": "monsters_m",
      "file": "src/gvars/utils/catalogues/monsters/monsters_m.gvar.json",
      "id": "2c9afcd4-e811-4e4d-8093-cfb36ec23a0c"
    },
    {
      "name": "monsters_n",
      "file": "src/gvars/utils/catalogues/monsters/monsters_n.gvar.json",
      "id": "f8a462b7-39a3-4dfb-8735-0423578ea83e"
    },
    {
      "name": "monsters_o",
      "file": "src/gvars/utils/catalogues/monsters/monsters_o.gvar.json",
      "id": "dfa9b97e-5141-44e4-869b-f60fceaa32dc"
    },
    {
      "name": "monsters_p",
      "file": "src/gvars/utils/catalogues/monsters/monsters_p.gvar.json",
      "id": "6dfb76b0-7793-4149-b209-9c3bcc5e60be"
    },
    {
      "name": "monsters_q",
      "file": "src/gvars/utils/catalogues/monsters/monsters_q.gvar.json",
      "id": "f36fdf90-8d35-4e6c-add2-f68bc37cbd1e"
    },
    {
      "name": "monsters_r",
      "file": "src/gvars/utils/catalogues/monsters/monsters_r.gvar.json",
      "id": "4eb2ec86-4bb4-4884-952b-c822c5320c84"
    },
    {
      "name": "monsters_s",
      "file": "src/gvars/utils/catalogues/monsters/monsters_s.gvar.json",
      "id": "56fab4ee-0246-4441-b5a7-556b563daba9"
    },
    {
      "name": "monsters_t",
      "file": "src/gvars/utils/catalogues/monsters/monsters_t.gvar.json",
      "id": "04710412-6914-422d-ab2b-5574ccbe0b77"
    },
    {
      "name": "monsters_u",
      "file": "src/gvars/utils/catalogues/monsters/monsters_u.gvar.json",
      "id": "23fef75b-997b-40b7-9630-ef45a8ae67a2"
    },
    {
      "name": "monsters_v",
      "file": "src/gvars/utils/catalogues/monsters/monsters_v.gvar.json",
      "id": "23820b8e-c725-45fa-9a27-4005931059bc"
    },
    {
      "name": "monsters_w",
      "file": "src/gvars/utils/catalogues/monsters/monsters_w.gvar.json",
      "id": "f8449119-206a-4a05-8140-2bebc25eb8ee"
    },
    {
      "name": "monsters_x",
      "file": "src/gvars/utils/catalogues/monsters/monsters_x.gvar.json",
      "id": "2149d241-dd11-401c-8757-0cfa308a44a7"
    },
    {
      "name": "monsters_y",
      "file": "src/gvars/utils/catalogues/monsters/monsters_y.gvar.json",
      "id": "cf7e2fd2-6be9-44f7-bb1d-e71b720e42c9"
    },
    {
      "name": "monsters_z",
      "file": "src/gvars/utils/catalogues/monsters/monsters_z.gvar.json",
      "id": "6f366ec0-1337-43ac-a325-d9316c1cfe94"
    },
    {
      "name": "paths",
      "file": "src/gvars/utils/world/paths.gvar",
      "id": "c6875cce-8c86-486e-ba75-7c0f8963b889"
    },
    {
      "name": "pc",
      "file": "src/gvars/utils/pc/pc.gvar",
      "id": "a6dab2a6-dd73-4ee4-a6d9-668236faab04"
    },
    {
      "name": "potions_list",
      "file": "src/gvars/utils/catalogues/items/potions_list.gvar.json",
      "id": "2ed21b7e-cb0f-46dd-bb2c-31a4b05df641"
    },
    {
      "name": "quests",
      "file": "src/gvars/utils/misc/quests.gvar",
      "id": "46ee044d-1b95-437a-8cf5-66f9320e04e0"
    },
    {
      "name": "random",
      "file": "src/gvars/utils/core/random.gvar",
      "id": "f7184e4a-95e0-4ef1-83ad-b2dc6ca57e89"
    },
    {
      "name": "recipe",
      "file": "src/gvars/utils/misc/recipe.gvar",
      "id": "d667bf05-88ad-4379-9ae6-bc91466eb3ea"
    },
    {
      "name": "recipes_list",
      "file": "src/gvars/configs/recipes/recipes_list.gvar.json",
      "id": "58a8ab6d-1441-44a6-baef-f7e3f089583a"
    },
    {
      "name": "regex",
      "file": "src/gvars/utils/core/regex.gvar",
      "id": "20ad4399-8662-4ea6-afb5-339bed44acbe"
    },
    {
      "name": "rolls",
      "file": "src/gvars/utils/core/rolls.gvar",
      "id": "d769f5a0-fbf9-4bde-88d0-b8de49bb9936"
    },
    {
      "name": "shops",
      "file": "src/gvars/utils/economy/shops.gvar",
      "id": "8b5f6144-89d4-4bac-b28f-551158f510bb"
    },
    {
      "name": "spells",
      "file": "src/gvars/utils/catalogues/spells/spells.gvar",
      "id": "7ebd040c-28de-4304-9c49-f16242d3e261"
    },
    {
      "name": "spells_list",
      "file": "src/gvars/utils/catalogues/spells/spells_list.gvar.json",
      "id": "bc60c8c7-df51-4e28-8e9b-51ad5438edf4"
    },
    {
      "name": "stats",
      "file": "src/gvars/utils/pc/stats.gvar",
      "id": "c0b0f9c3-23ed-437e-a248-98bb448dcd96"
    },
    {
      "name": "strings",
      "file": "src/gvars/utils/core/strings.gvar",
      "id": "1094cf3c-8b5f-4ea7-b5d6-ae18bc66680a"
    },
    {
      "name": "time",
      "file": "src/gvars/utils/core/time.gvar",
      "id": "fbf9e239-21e4-4de3-a4f1-251e677fa5ea"
    },
    {
      "name": "tools",
      "file": "src/gvars/utils/core/tools.gvar",
      "id": "d1e91227-938b-4c65-a8fd-b3d98ed32fb7"
    },
    {
      "name": "weather",
      "file": "src/gvars/utils/world/weather.gvar",
      "id": "d074b25e-9d6b-4588-ac0c-07bdff78eed5"
    },
    {
      "name": "westmarch_2014_locations",
      "file": "src/gvars/configs/westmarch_2014_locations.gvar.json",
      "id": "97a48b87-f253-4feb-90ae-4e4675ba533d"
    },
    {
      "name": "westmarch_2014_paths",
      "file": "src/gvars/configs/westmarch_2014_paths.gvar.json",
      "id": "f0243c7a-79af-4ecf-a81b-c9a8df266bb3"
    }
  ]
}
